seacorenlp/__init__.py
seacorenlp/__main__.py
seacorenlp/constants.py
seacorenlp/utils.py
seacorenlp/data/__init__.py
seacorenlp/data/tokenizers/__init__.py
seacorenlp/data/tokenizers/custom_tokenizer.py
seacorenlp/data/tokenizers/sentence_splitter.py
seacorenlp/data/tokenizers/stanza_tokenizer.py
seacorenlp/models/__init__.py
seacorenlp/models/base_predictor.py
seacorenlp/models/base_segmenter.py
seacorenlp/parsing/__init__.py
seacorenlp/parsing/constituency/__init__.py
seacorenlp/parsing/constituency/benepar_parser.py
seacorenlp/parsing/constituency/custom_parser.py
seacorenlp/parsing/constituency/training/__init__.py
seacorenlp/parsing/constituency/training/predictor.py
seacorenlp/parsing/dependency/__init__.py
seacorenlp/parsing/dependency/custom_parser.py
seacorenlp/parsing/dependency/training/__init__.py
seacorenlp/parsing/dependency/training/predictor.py
seacorenlp/tagging/__init__.py
seacorenlp/tagging/ner/__init__.py
seacorenlp/tagging/ner/custom_tagger.py
seacorenlp/tagging/ner/training/__init__.py
seacorenlp/tagging/ner/training/predictor.py
seacorenlp/tagging/ner/training/dataset_readers/__init__.py
seacorenlp/tagging/ner/training/dataset_readers/indonesian.py
seacorenlp/tagging/ner/training/dataset_readers/thai.py
seacorenlp/tagging/pos/__init__.py
seacorenlp/tagging/pos/custom_tagger.py
seacorenlp/tagging/pos/stanza_tagger.py
seacorenlp/tagging/pos/training/__init__.py
seacorenlp/tagging/pos/training/dataset_reader.py
seacorenlp/tagging/pos/training/model.py
seacorenlp/tagging/pos/training/predictor.py
seacorenlp/training_resources/config/parsing/constituency/config.jsonnet
seacorenlp/training_resources/config/parsing/dependency/config.jsonnet
seacorenlp/training_resources/config/tagging/ner/config.jsonnet
seacorenlp/training_resources/config/tagging/pos/config.jsonnet
seacorenlp-0.0.2.dist-info/LICENSE
seacorenlp-0.0.2.dist-info/METADATA
seacorenlp-0.0.2.dist-info/WHEEL
seacorenlp-0.0.2.dist-info/entry_points.txt
seacorenlp-0.0.2.dist-info/top_level.txt
seacorenlp-0.0.2.dist-info/RECORD
