Metadata-Version: 2.1
Name: seacorenlp
Version: 0.0.2
Summary: SEACoreNLP: A Python NLP Toolkit for Southeast Asian languages
Home-page: UNKNOWN
Author: Wei Qi Leong, Arie Pratama Sutiono
Author-email: seacorenlp@aisingapore.org
License: GNU General Public License v3 (GPLv3)
Keywords: NLP,Thai,Vietnamese,Indonesian,Malay,POS Tagging,NER,Constituency Parsing,Dependency Parsing
Platform: UNKNOWN
Classifier: Development Status :: 4 - Beta
Classifier: Programming Language :: Python :: 3
Classifier: Programming Language :: Python :: 3.7
Classifier: License :: OSI Approved :: GNU General Public License v3 (GPLv3)
Classifier: Natural Language :: Indonesian
Classifier: Natural Language :: Thai
Classifier: Natural Language :: Vietnamese
Classifier: Topic :: Scientific/Engineering :: Artificial Intelligence
Requires-Python: >=3.7
Requires-Dist: allennlp (==1.5.0)
Requires-Dist: allennlp-models (==1.5.0)
Requires-Dist: attacut (==1.0.6)
Requires-Dist: benepar (==0.2.0)
Requires-Dist: pythainlp (==2.2.5)
Requires-Dist: malaya (==4.0)
Requires-Dist: networkx (==2.5)
Requires-Dist: spacy-thai (==0.6.0)
Requires-Dist: ssg (==0.0.6)
Requires-Dist: stanza (==1.1.1)
Requires-Dist: underthesea (==1.2.3)
